catalog/__init__.py
catalog/version.py
catalog/api/__init__.py
catalog/api/api.py
catalog/database/__init__.py
catalog/database/db.py
catalog/database/mars2020.py
catalog/image/__init__.py
catalog/image/rgb.py
catalog/misc/__init__.py
catalog/misc/logger.py
catalog/misc/now.py
mars_rovers_catalog-0.1.0.dist-info/LICENCE.md
mars_rovers_catalog-0.1.0.dist-info/METADATA
mars_rovers_catalog-0.1.0.dist-info/WHEEL
mars_rovers_catalog-0.1.0.dist-info/top_level.txt
mars_rovers_catalog-0.1.0.dist-info/RECORD
