Metadata-Version: 2.1
Name: mars-rovers-catalog
Version: 0.1.0
Summary: Mars Rovers Catalog toolbox
Home-page: https://gitlab.univ-nantes.fr/mars-rovers/catalog/
Author: Benoit Seignovert
Author-email: benoit.seignovert@univ-nantes.fr
License: BSD
Keywords: nasa,catalog,mars2020,perseverance,msl,curiosity
Platform: UNKNOWN
Classifier: Development Status :: 3 - Alpha
Classifier: Intended Audience :: Developers
Classifier: Intended Audience :: Science/Research
Classifier: License :: OSI Approved :: BSD License
Classifier: Natural Language :: English
Classifier: Programming Language :: Python
Classifier: Programming Language :: Python :: 3.8
Classifier: Programming Language :: Python :: 3.9
Classifier: Topic :: Scientific/Engineering
Classifier: Topic :: Scientific/Engineering :: Astronomy
Requires-Python: >=3.6
Requires-Dist: requests
Requires-Dist: Pillow (>=8.0)
Requires-Dist: ipython
